kuba/__init__.py
kuba/cli.py
kuba-0.22.0.dist-info/METADATA
kuba-0.22.0.dist-info/WHEEL
kuba-0.22.0.dist-info/entry_points.txt
kuba-0.22.0.dist-info/RECORD
