Metadata-Version: 2.1
Name: kuba
Version: 0.22.0
Summary: The kuba-mazing kubectl companion
Author: Hunter Gatewood
Author-email: hgatewood@gmail.com
Requires-Python: >=3.12,<4.0
Classifier: Programming Language :: Python :: 3
Classifier: Programming Language :: Python :: 3.12
Requires-Dist: click (>=8.0.0,<9.0.0)
Requires-Dist: hcgatewood_coda (>=1.0.0,<2.0.0)
Requires-Dist: pyyaml (>=6.0,<7.0)
